fastapply_mcp/__init__.py
fastapply_mcp/main.py
fastapply_mcp/py.typed
fastapply_mcp-1.1.1.dist-info/METADATA
fastapply_mcp-1.1.1.dist-info/WHEEL
fastapply_mcp-1.1.1.dist-info/entry_points.txt
fastapply_mcp-1.1.1.dist-info/RECORD
