Metadata-Version: 2.4
Name: fastapply_mcp
Version: 1.1.1
Summary: MCP server for AI-powered code editing through FastApply integration
Author: tickernelz
License: MIT
Keywords: ai,code-editing,fastapply,llm,mcp
Classifier: Development Status :: 4 - Beta
Classifier: Intended Audience :: Developers
Classifier: License :: OSI Approved :: MIT License
Classifier: Programming Language :: Python :: 3
Classifier: Programming Language :: Python :: 3.13
Classifier: Topic :: Software Development :: Code Generators
Requires-Python: >=3.13
Requires-Dist: mcp[cli]>=1.14.1
Requires-Dist: openai>=1.108.0
Requires-Dist: python-dotenv>=1.1.1
Requires-Dist: structlog>=25.4.0
Provides-Extra: dev
Requires-Dist: mypy>=1.18.2; extra == 'dev'
Requires-Dist: ruff>=0.13.1; extra == 'dev'
